cls/__init__.py
cls/base.py
test_cls/__init__.py
test_cls/test_base.py
acls-1.0.0.dist-info/LICENSE
acls-1.0.0.dist-info/METADATA
acls-1.0.0.dist-info/WHEEL
acls-1.0.0.dist-info/top_level.txt
acls-1.0.0.dist-info/RECORD
